pymatrix/__init__.py
pymatrix_ss-0.1.8.dist-info/entry_points.txt
pymatrix_ss-0.1.8.dist-info/LICENSE
pymatrix_ss-0.1.8.dist-info/WHEEL
pymatrix_ss-0.1.8.dist-info/METADATA
pymatrix_ss-0.1.8.dist-info/RECORD
