Metadata-Version: 2.1
Name: pymatrix-ss
Version: 0.1.8
Summary: 
Home-page: https://github.com/m9810223/pymatrix-ss
Author:  
Requires-Python: >3,<4
Classifier: Programming Language :: Python :: 3
Classifier: Programming Language :: Python :: 3.10
Classifier: Programming Language :: Python :: 3.4
Classifier: Programming Language :: Python :: 3.5
Classifier: Programming Language :: Python :: 3.6
Classifier: Programming Language :: Python :: 3.7
Classifier: Programming Language :: Python :: 3.8
Classifier: Programming Language :: Python :: 3.9
Project-URL: Repository, https://github.com/m9810223/pymatrix-ss
